invoke-stubs/METADATA.toml
invoke-stubs/__init__.pyi
invoke-stubs/collection.pyi
invoke-stubs/config.pyi
invoke-stubs/context.pyi
invoke-stubs/env.pyi
invoke-stubs/exceptions.pyi
invoke-stubs/executor.pyi
invoke-stubs/loader.pyi
invoke-stubs/main.pyi
invoke-stubs/program.pyi
invoke-stubs/runners.pyi
invoke-stubs/tasks.pyi
invoke-stubs/terminals.pyi
invoke-stubs/util.pyi
invoke-stubs/watchers.pyi
invoke-stubs/completion/__init__.pyi
invoke-stubs/completion/complete.pyi
invoke-stubs/parser/__init__.pyi
invoke-stubs/parser/argument.pyi
invoke-stubs/parser/context.pyi
invoke-stubs/parser/parser.pyi
types_invoke-2.0.0.9.dist-info/METADATA
types_invoke-2.0.0.9.dist-info/WHEEL
types_invoke-2.0.0.9.dist-info/top_level.txt
types_invoke-2.0.0.9.dist-info/RECORD
